{
  "last_updated": "2026-01-06T03:11:35Z",
  "accounts": [
    {
      "id": "0",
      "login": 0,
      "name": "",
      "server": "",
      "currency": "",
      "balance": 6727.3,
      "equity": 6727.3,
      "margin": 0,
      "free_margin": 6727.3,
      "margin_level": 0,
      "profit": 0,
      "last_updated": "2026-01-05T16:47:31Z",
      "active_eas": [
        "GoldenTrade"
      ]
    },
    {
      "id": "20158621",
      "login": 20158621,
      "name": "Eric Lanvin",
      "server": "WindsorBrokers1-Demo",
      "currency": "USC",
      "balance": 12405.31,
      "equity": 12397.7,
      "margin": 7.5,
      "free_margin": 12390.2,
      "margin_level": 165302.67,
      "profit": -7.61,
      "last_updated": "2026-01-06T02:38:27Z",
      "active_eas": [
        "EA Trade Helper"
      ]
    },
    {
      "id": "80063754",
      "login": 80063754,
      "name": "HENDRA ROHENDI",
      "server": "WindsorBrokers1-Real1",
      "currency": "USC",
      "balance": 38638.5,
      "equity": 40218.75,
      "margin": 667.39,
      "free_margin": 39551.36,
      "margin_level": 6026.27,
      "profit": 1580.25,
      "last_updated": "2026-01-06T03:11:30Z",
      "active_eas": [
        "GoldenTrade"
      ]
    },
    {
      "id": "80068538",
      "login": 80068538,
      "name": "EKA RITAWATI",
      "server": "WindsorBrokers1-Real1",
      "currency": "USC",
      "balance": 9895.18,
      "equity": 9895.18,
      "margin": 0,
      "free_margin": 9895.18,
      "margin_level": 0,
      "profit": 0,
      "last_updated": "2026-01-05T15:38:37Z",
      "active_eas": [
        "EA Trade Helper"
      ]
    },
    {
      "id": "80075738",
      "login": 80075738,
      "name": "EKA RITAWATI",
      "server": "WindsorBrokers1-Real1",
      "currency": "USC",
      "balance": 0.36,
      "equity": 0.36,
      "margin": 0,
      "free_margin": 0.36,
      "margin_level": 0,
      "profit": 0,
      "last_updated": "2026-01-05T15:37:41Z",
      "active_eas": [
        "EA Trade Helper"
      ]
    },
    {
      "id": "80076323",
      "login": 80076323,
      "name": "Windsor cent 3",
      "server": "WITITSolutionsLtd-Real1",
      "currency": "USC",
      "balance": 10379.7,
      "equity": 10377.18,
      "margin": 4.86,
      "free_margin": 10372.32,
      "margin_level": 213522.22,
      "profit": -2.52,
      "last_updated": "2026-01-05T07:14:48Z",
      "active_eas": [
        "EA Trade Helper"
      ]
    },
    {
      "id": "80076324",
      "login": 80076324,
      "name": "Windsor cent 4",
      "server": "WITITSolutionsLtd-Real1",
      "currency": "USC",
      "balance": 7296.85,
      "equity": 7247.43,
      "margin": 80.14,
      "free_margin": 7167.29,
      "margin_level": 9043.46,
      "profit": -49.42,
      "last_updated": "2026-01-06T02:10:22Z",
      "active_eas": [
        "EA Trade Helper"
      ]
    },
    {
      "id": "80140550",
      "login": 80140550,
      "name": "Aksan Imanuddin Rahim",
      "server": "WindsorBrokers1-Real1",
      "currency": "USC",
      "balance": 14309.3,
      "equity": 14831.55,
      "margin": 222.46,
      "free_margin": 14609.09,
      "margin_level": 6667.06,
      "profit": 522.25,
      "last_updated": "2026-01-06T03:11:14Z",
      "active_eas": [
        "GoldenTrade"
      ]
    },
    {
      "id": "80144430",
      "login": 80144430,
      "name": "rusnaini rusnaini",
      "server": "WindsorBrokers1-Real1",
      "currency": "USC",
      "balance": 33354,
      "equity": 34931.25,
      "margin": 667.39,
      "free_margin": 34263.86,
      "margin_level": 5234.01,
      "profit": 1577.25,
      "last_updated": "2026-01-06T03:11:35Z",
      "active_eas": [
        "GoldenTrade"
      ]
    },
    {
      "id": "80144436",
      "login": 80144436,
      "name": "fikri fikri",
      "server": "WindsorBrokers1-Real1",
      "currency": "USC",
      "balance": 5748.7,
      "equity": 5919.7,
      "margin": 88.99,
      "free_margin": 5830.71,
      "margin_level": 6652.1,
      "profit": 171,
      "last_updated": "2026-01-06T03:06:52Z",
      "active_eas": [
        "GoldenTrade"
      ]
    },
    {
      "id": "80144607",
      "login": 80144607,
      "name": "Cross Masarel Lamgogo B",
      "server": "WindsorBrokers1-Real1",
      "currency": "USC",
      "balance": 5285.8,
      "equity": 5492.2,
      "margin": 0,
      "free_margin": 5492.2,
      "margin_level": 0,
      "profit": 206.4,
      "last_updated": "2026-01-06T03:08:41Z",
      "active_eas": [
        "GoldenTrade"
      ]
    },
    {
      "id": "80144917",
      "login": 80144917,
      "name": "imran imran",
      "server": "WindsorBrokers1-Real1",
      "currency": "USC",
      "balance": 3183.6,
      "equity": 3278.6,
      "margin": 44.49,
      "free_margin": 3234.11,
      "margin_level": 7369.3,
      "profit": 95,
      "last_updated": "2026-01-06T03:08:45Z",
      "active_eas": [
        "GoldenTrade"
      ]
    },
    {
      "id": "80145055",
      "login": 80145055,
      "name": "putri nurlita dewi",
      "server": "WindsorBrokers1-Real1",
      "currency": "USC",
      "balance": 13515.8,
      "equity": 14157,
      "margin": 311.45,
      "free_margin": 13845.55,
      "margin_level": 4545.51,
      "profit": 641.2,
      "last_updated": "2026-01-06T03:07:46Z",
      "active_eas": [
        "GoldenTrade"
      ]
    },
    {
      "id": "80145216",
      "login": 80145216,
      "name": "Ardans Ardans",
      "server": "WindsorBrokers1-Real1",
      "currency": "USC",
      "balance": 10287.8,
      "equity": 10702.7,
      "margin": 0,
      "free_margin": 10702.7,
      "margin_level": 0,
      "profit": 414.9,
      "last_updated": "2026-01-06T03:07:31Z",
      "active_eas": [
        "GoldenTrade"
      ]
    },
    {
      "id": "80145228",
      "login": 80145228,
      "name": "FAISAL FAISAL",
      "server": "WindsorBrokers1-Real1",
      "currency": "USC",
      "balance": 6305.5,
      "equity": 6590.65,
      "margin": 133.48,
      "free_margin": 6457.17,
      "margin_level": 4937.56,
      "profit": 285.15,
      "last_updated": "2026-01-06T03:08:46Z",
      "active_eas": [
        "GoldenTrade"
      ]
    },
    {
      "id": "80145487",
      "login": 80145487,
      "name": "DWI APRIADI",
      "server": "WindsorBrokers1-Real1",
      "currency": "USC",
      "balance": 3183.6,
      "equity": 3282.35,
      "margin": 44.49,
      "free_margin": 3237.86,
      "margin_level": 7377.73,
      "profit": 98.75,
      "last_updated": "2026-01-06T03:09:31Z",
      "active_eas": [
        "GoldenTrade"
      ]
    },
    {
      "id": "80145852",
      "login": 80145852,
      "name": "muhammad nasir",
      "server": "WindsorBrokers1-Real1",
      "currency": "USC",
      "balance": 2759.4,
      "equity": 2864.95,
      "margin": 44.49,
      "free_margin": 2820.46,
      "margin_level": 6439.54,
      "profit": 105.55,
      "last_updated": "2026-01-06T03:11:08Z",
      "active_eas": [
        "GoldenTrade"
      ]
    },
    {
      "id": "103183855",
      "login": 103183855,
      "name": "Abi Manyu",
      "server": "FBS-Demo",
      "currency": "USD",
      "balance": 9989.83,
      "equity": 9985.43,
      "margin": 29.38,
      "free_margin": 9956.05,
      "margin_level": 33987.17,
      "profit": -4.4,
      "last_updated": "2026-01-04T08:42:25Z",
      "active_eas": [
        "EA Trade Helper",
        "GoldenTrade"
      ]
    }
  ]
}