{
  "last_updated": "2026-01-06T02:36:51Z",
  "accounts": [
    {
      "id": "0",
      "login": 0,
      "name": "",
      "server": "",
      "currency": "",
      "balance": 6727.3,
      "equity": 6727.3,
      "margin": 0,
      "free_margin": 6727.3,
      "margin_level": 0,
      "profit": 0,
      "last_updated": "2026-01-05T16:47:31Z",
      "active_eas": [
        "GoldenTrade"
      ]
    },
    {
      "id": "20158621",
      "login": 20158621,
      "name": "Eric Lanvin",
      "server": "WindsorBrokers1-Demo",
      "currency": "USC",
      "balance": 12405.31,
      "equity": 12400.87,
      "margin": 3.75,
      "free_margin": 12397.12,
      "margin_level": 330689.87,
      "profit": -4.44,
      "last_updated": "2026-01-06T02:31:34Z",
      "active_eas": [
        "EA Trade Helper"
      ]
    },
    {
      "id": "80063754",
      "login": 80063754,
      "name": "HENDRA ROHENDI",
      "server": "WindsorBrokers1-Real1",
      "currency": "USC",
      "balance": 38638.5,
      "equity": 40200.75,
      "margin": 667.39,
      "free_margin": 39533.36,
      "margin_level": 6023.58,
      "profit": 1562.25,
      "last_updated": "2026-01-06T02:36:29Z",
      "active_eas": [
        "GoldenTrade"
      ]
    },
    {
      "id": "80068538",
      "login": 80068538,
      "name": "EKA RITAWATI",
      "server": "WindsorBrokers1-Real1",
      "currency": "USC",
      "balance": 9895.18,
      "equity": 9895.18,
      "margin": 0,
      "free_margin": 9895.18,
      "margin_level": 0,
      "profit": 0,
      "last_updated": "2026-01-05T15:38:37Z",
      "active_eas": [
        "EA Trade Helper"
      ]
    },
    {
      "id": "80075738",
      "login": 80075738,
      "name": "EKA RITAWATI",
      "server": "WindsorBrokers1-Real1",
      "currency": "USC",
      "balance": 0.36,
      "equity": 0.36,
      "margin": 0,
      "free_margin": 0.36,
      "margin_level": 0,
      "profit": 0,
      "last_updated": "2026-01-05T15:37:41Z",
      "active_eas": [
        "EA Trade Helper"
      ]
    },
    {
      "id": "80076323",
      "login": 80076323,
      "name": "Windsor cent 3",
      "server": "WITITSolutionsLtd-Real1",
      "currency": "USC",
      "balance": 10379.7,
      "equity": 10377.18,
      "margin": 4.86,
      "free_margin": 10372.32,
      "margin_level": 213522.22,
      "profit": -2.52,
      "last_updated": "2026-01-05T07:14:48Z",
      "active_eas": [
        "EA Trade Helper"
      ]
    },
    {
      "id": "80076324",
      "login": 80076324,
      "name": "Windsor cent 4",
      "server": "WITITSolutionsLtd-Real1",
      "currency": "USC",
      "balance": 7296.85,
      "equity": 7247.43,
      "margin": 80.14,
      "free_margin": 7167.29,
      "margin_level": 9043.46,
      "profit": -49.42,
      "last_updated": "2026-01-06T02:10:22Z",
      "active_eas": [
        "EA Trade Helper"
      ]
    },
    {
      "id": "80140550",
      "login": 80140550,
      "name": "Aksan Imanuddin Rahim",
      "server": "WindsorBrokers1-Real1",
      "currency": "USC",
      "balance": 14309.3,
      "equity": 14804.05,
      "margin": 222.46,
      "free_margin": 14581.59,
      "margin_level": 6654.7,
      "profit": 494.75,
      "last_updated": "2026-01-06T02:36:13Z",
      "active_eas": [
        "GoldenTrade"
      ]
    },
    {
      "id": "80144430",
      "login": 80144430,
      "name": "rusnaini rusnaini",
      "server": "WindsorBrokers1-Real1",
      "currency": "USC",
      "balance": 33354,
      "equity": 34950.75,
      "margin": 667.39,
      "free_margin": 34283.36,
      "margin_level": 5236.93,
      "profit": 1596.75,
      "last_updated": "2026-01-06T02:36:36Z",
      "active_eas": [
        "GoldenTrade"
      ]
    },
    {
      "id": "80144436",
      "login": 80144436,
      "name": "fikri fikri",
      "server": "WindsorBrokers1-Real1",
      "currency": "USC",
      "balance": 5748.7,
      "equity": 5956.4,
      "margin": 88.99,
      "free_margin": 5867.41,
      "margin_level": 6693.34,
      "profit": 207.7,
      "last_updated": "2026-01-06T02:36:51Z",
      "active_eas": [
        "GoldenTrade"
      ]
    },
    {
      "id": "80144607",
      "login": 80144607,
      "name": "Cross Masarel Lamgogo B",
      "server": "WindsorBrokers1-Real1",
      "currency": "USC",
      "balance": 5285.8,
      "equity": 5490.85,
      "margin": 0,
      "free_margin": 5490.85,
      "margin_level": 0,
      "profit": 205.05,
      "last_updated": "2026-01-06T02:33:40Z",
      "active_eas": [
        "GoldenTrade"
      ]
    },
    {
      "id": "80144917",
      "login": 80144917,
      "name": "imran imran",
      "server": "WindsorBrokers1-Real1",
      "currency": "USC",
      "balance": 3183.6,
      "equity": 3277.15,
      "margin": 44.49,
      "free_margin": 3232.66,
      "margin_level": 7366.04,
      "profit": 93.55,
      "last_updated": "2026-01-06T02:33:45Z",
      "active_eas": [
        "GoldenTrade"
      ]
    },
    {
      "id": "80145055",
      "login": 80145055,
      "name": "putri nurlita dewi",
      "server": "WindsorBrokers1-Real1",
      "currency": "USC",
      "balance": 13515.8,
      "equity": 14211.6,
      "margin": 311.45,
      "free_margin": 13900.15,
      "margin_level": 4563.04,
      "profit": 695.8,
      "last_updated": "2026-01-06T02:32:45Z",
      "active_eas": [
        "GoldenTrade"
      ]
    },
    {
      "id": "80145216",
      "login": 80145216,
      "name": "Ardans Ardans",
      "server": "WindsorBrokers1-Real1",
      "currency": "USC",
      "balance": 10287.8,
      "equity": 10700.6,
      "margin": 0,
      "free_margin": 10700.6,
      "margin_level": 0,
      "profit": 412.8,
      "last_updated": "2026-01-06T02:32:31Z",
      "active_eas": [
        "GoldenTrade"
      ]
    },
    {
      "id": "80145228",
      "login": 80145228,
      "name": "FAISAL FAISAL",
      "server": "WindsorBrokers1-Real1",
      "currency": "USC",
      "balance": 6305.5,
      "equity": 6594.1,
      "margin": 133.48,
      "free_margin": 6460.62,
      "margin_level": 4940.14,
      "profit": 288.6,
      "last_updated": "2026-01-06T02:33:46Z",
      "active_eas": [
        "GoldenTrade"
      ]
    },
    {
      "id": "80145487",
      "login": 80145487,
      "name": "DWI APRIADI",
      "server": "WindsorBrokers1-Real1",
      "currency": "USC",
      "balance": 3183.6,
      "equity": 3286.1,
      "margin": 44.49,
      "free_margin": 3241.61,
      "margin_level": 7386.15,
      "profit": 102.5,
      "last_updated": "2026-01-06T02:34:31Z",
      "active_eas": [
        "GoldenTrade"
      ]
    },
    {
      "id": "80145852",
      "login": 80145852,
      "name": "muhammad nasir",
      "server": "WindsorBrokers1-Real1",
      "currency": "USC",
      "balance": 2759.4,
      "equity": 2855.25,
      "margin": 44.49,
      "free_margin": 2810.76,
      "margin_level": 6417.73,
      "profit": 95.85,
      "last_updated": "2026-01-06T02:36:08Z",
      "active_eas": [
        "GoldenTrade"
      ]
    },
    {
      "id": "103183855",
      "login": 103183855,
      "name": "Abi Manyu",
      "server": "FBS-Demo",
      "currency": "USD",
      "balance": 9989.83,
      "equity": 9985.43,
      "margin": 29.38,
      "free_margin": 9956.05,
      "margin_level": 33987.17,
      "profit": -4.4,
      "last_updated": "2026-01-04T08:42:25Z",
      "active_eas": [
        "EA Trade Helper",
        "GoldenTrade"
      ]
    }
  ]
}