{
  "last_updated": "2026-01-12T11:15:12Z",
  "accounts": [
    {
      "id": "0",
      "login": 0,
      "name": "",
      "server": "",
      "currency": "",
      "balance": 6727.3,
      "equity": 6727.3,
      "margin": 0,
      "free_margin": 6727.3,
      "margin_level": 0,
      "profit": 0,
      "last_updated": "2026-01-05T16:47:31Z",
      "active_eas": [
        "GoldenTrade"
      ]
    },
    {
      "id": "20158621",
      "login": 20158621,
      "name": "Eric Lanvin",
      "server": "WindsorBrokers1-Demo",
      "currency": "USC",
      "balance": 13567.45,
      "equity": 13043.1,
      "margin": 161.79,
      "free_margin": 12881.31,
      "margin_level": 8061.75,
      "profit": -524.35,
      "last_updated": "2026-01-12T10:55:44Z",
      "active_eas": [
        "EA Trade Helper"
      ]
    },
    {
      "id": "80063754",
      "login": 80063754,
      "name": "HENDRA ROHENDI",
      "server": "WindsorBrokers1-Real1",
      "currency": "USC",
      "balance": 37560,
      "equity": 37317,
      "margin": 689.2,
      "free_margin": 36627.8,
      "margin_level": 5414.54,
      "profit": -243,
      "last_updated": "2026-01-12T11:14:25Z",
      "active_eas": [
        "GoldenTrade"
      ]
    },
    {
      "id": "80068538",
      "login": 80068538,
      "name": "EKA RITAWATI",
      "server": "WindsorBrokers1-Real1",
      "currency": "USC",
      "balance": 9895.18,
      "equity": 9895.18,
      "margin": 0,
      "free_margin": 9895.18,
      "margin_level": 0,
      "profit": 0,
      "last_updated": "2026-01-05T15:38:37Z",
      "active_eas": [
        "EA Trade Helper"
      ]
    },
    {
      "id": "80075738",
      "login": 80075738,
      "name": "EKA RITAWATI",
      "server": "WindsorBrokers1-Real1",
      "currency": "USC",
      "balance": 0.36,
      "equity": 0.36,
      "margin": 0,
      "free_margin": 0.36,
      "margin_level": 0,
      "profit": 0,
      "last_updated": "2026-01-05T15:37:41Z",
      "active_eas": [
        "EA Trade Helper"
      ]
    },
    {
      "id": "80076323",
      "login": 80076323,
      "name": "Windsor cent 3",
      "server": "WITITSolutionsLtd-Real1",
      "currency": "USC",
      "balance": 10379.7,
      "equity": 10377.18,
      "margin": 4.86,
      "free_margin": 10372.32,
      "margin_level": 213522.22,
      "profit": -2.52,
      "last_updated": "2026-01-05T07:14:48Z",
      "active_eas": [
        "EA Trade Helper"
      ]
    },
    {
      "id": "80076324",
      "login": 80076324,
      "name": "Windsor cent 4",
      "server": "WITITSolutionsLtd-Real1",
      "currency": "USC",
      "balance": 6828.37,
      "equity": 6828.37,
      "margin": 0,
      "free_margin": 6828.37,
      "margin_level": 0,
      "profit": 0,
      "last_updated": "2026-01-12T10:15:58Z",
      "active_eas": [
        "EA Trade Helper"
      ]
    },
    {
      "id": "80140550",
      "login": 80140550,
      "name": "Aksan Imanuddin Rahim",
      "server": "WindsorBrokers1-Real1",
      "currency": "USC",
      "balance": 12134.55,
      "equity": 12288.3,
      "margin": 458.77,
      "free_margin": 11829.53,
      "margin_level": 2678.53,
      "profit": 153.75,
      "last_updated": "2026-01-12T11:15:03Z",
      "active_eas": [
        "GoldenTrade"
      ]
    },
    {
      "id": "80144430",
      "login": 80144430,
      "name": "rusnaini rusnaini",
      "server": "WindsorBrokers1-Real1",
      "currency": "USC",
      "balance": 33939.75,
      "equity": 33992.25,
      "margin": 0,
      "free_margin": 33992.25,
      "margin_level": 0,
      "profit": 52.5,
      "last_updated": "2026-01-12T11:14:23Z",
      "active_eas": [
        "GoldenTrade"
      ]
    },
    {
      "id": "80144436",
      "login": 80144436,
      "name": "fikri fikri",
      "server": "WindsorBrokers1-Real1",
      "currency": "USC",
      "balance": 6087.4,
      "equity": 6128.5,
      "margin": 183.56,
      "free_margin": 5944.94,
      "margin_level": 3338.69,
      "profit": 41.1,
      "last_updated": "2026-01-12T11:14:35Z",
      "active_eas": [
        "GoldenTrade"
      ]
    },
    {
      "id": "80144607",
      "login": 80144607,
      "name": "Cross Masarel Lamgogo B",
      "server": "WindsorBrokers1-Real1",
      "currency": "USC",
      "balance": 8929.85,
      "equity": 9002.45,
      "margin": 275.34,
      "free_margin": 8727.11,
      "margin_level": 3269.58,
      "profit": 72.6,
      "last_updated": "2026-01-12T11:14:25Z",
      "active_eas": [
        "GoldenTrade"
      ]
    },
    {
      "id": "80144917",
      "login": 80144917,
      "name": "imran imran",
      "server": "WindsorBrokers1-Real1",
      "currency": "USC",
      "balance": 3365.45,
      "equity": 3384.2,
      "margin": 91.78,
      "free_margin": 3292.42,
      "margin_level": 3687.3,
      "profit": 18.75,
      "last_updated": "2026-01-12T11:14:40Z",
      "active_eas": [
        "GoldenTrade"
      ]
    },
    {
      "id": "80145055",
      "login": 80145055,
      "name": "putri nurlita dewi",
      "server": "WindsorBrokers1-Real1",
      "currency": "USC",
      "balance": 15187.05,
      "equity": 15298,
      "margin": 642.46,
      "free_margin": 14655.54,
      "margin_level": 2381.16,
      "profit": 110.95,
      "last_updated": "2026-01-12T11:15:05Z",
      "active_eas": [
        "GoldenTrade"
      ]
    },
    {
      "id": "80145216",
      "login": 80145216,
      "name": "Ardans Ardans",
      "server": "WindsorBrokers1-Real1",
      "currency": "USC",
      "balance": 9765.8,
      "equity": 9789.2,
      "margin": 0,
      "free_margin": 9789.2,
      "margin_level": 0,
      "profit": 23.4,
      "last_updated": "2026-01-12T11:14:11Z",
      "active_eas": [
        "GoldenTrade"
      ]
    },
    {
      "id": "80145228",
      "login": 80145228,
      "name": "FAISAL FAISAL",
      "server": "WindsorBrokers1-Real1",
      "currency": "USC",
      "balance": 31115.4,
      "equity": 31128.4,
      "margin": 918.25,
      "free_margin": 30210.15,
      "margin_level": 3389.97,
      "profit": 13,
      "last_updated": "2026-01-12T11:14:21Z",
      "active_eas": [
        "GoldenTrade"
      ]
    },
    {
      "id": "80145487",
      "login": 80145487,
      "name": "DWI APRIADI",
      "server": "WindsorBrokers1-Real1",
      "currency": "USC",
      "balance": 3507.35,
      "equity": 3507.35,
      "margin": 0,
      "free_margin": 3507.35,
      "margin_level": 0,
      "profit": 0,
      "last_updated": "2026-01-12T11:14:29Z",
      "active_eas": [
        "GoldenTrade"
      ]
    },
    {
      "id": "80145852",
      "login": 80145852,
      "name": "muhammad nasir",
      "server": "WindsorBrokers1-Real1",
      "currency": "USC",
      "balance": 2926.4,
      "equity": 2943.85,
      "margin": 91.78,
      "free_margin": 2852.07,
      "margin_level": 3207.51,
      "profit": 17.45,
      "last_updated": "2026-01-12T11:14:42Z",
      "active_eas": [
        "GoldenTrade"
      ]
    },
    {
      "id": "80145993",
      "login": 80145993,
      "name": "asmah mp",
      "server": "WindsorBrokers1-Real1",
      "currency": "USC",
      "balance": 2270.8,
      "equity": 2294.85,
      "margin": 91.78,
      "free_margin": 2203.07,
      "margin_level": 2500.38,
      "profit": 24.05,
      "last_updated": "2026-01-12T11:14:28Z",
      "active_eas": [
        "GoldenTrade"
      ]
    },
    {
      "id": "80145997",
      "login": 80145997,
      "name": "Hj Suriani",
      "server": "WindsorBrokers1-Real1",
      "currency": "USC",
      "balance": 2270.3,
      "equity": 2285.5,
      "margin": 91.78,
      "free_margin": 2193.72,
      "margin_level": 2490.19,
      "profit": 15.2,
      "last_updated": "2026-01-12T11:14:39Z",
      "active_eas": [
        "GoldenTrade"
      ]
    },
    {
      "id": "80146009",
      "login": 80146009,
      "name": "Muhammad Sukriyadi",
      "server": "WindsorBrokers1-Real1",
      "currency": "USC",
      "balance": 5342,
      "equity": 5378.9,
      "margin": 183.56,
      "free_margin": 5195.34,
      "margin_level": 2930.32,
      "profit": 36.9,
      "last_updated": "2026-01-12T11:15:01Z",
      "active_eas": [
        "GoldenTrade"
      ]
    },
    {
      "id": "80146014",
      "login": 80146014,
      "name": "Arif Fadeli Badarrusmanto",
      "server": "WindsorBrokers1-Real1",
      "currency": "USC",
      "balance": 2770.8,
      "equity": 2783.65,
      "margin": 91.78,
      "free_margin": 2691.87,
      "margin_level": 3032.96,
      "profit": 12.85,
      "last_updated": "2026-01-12T11:15:10Z",
      "active_eas": [
        "GoldenTrade"
      ]
    },
    {
      "id": "80146232",
      "login": 80146232,
      "name": "suwardi dwi cahyono",
      "server": "WindsorBrokers1-Real1",
      "currency": "USC",
      "balance": 3170.8,
      "equity": 3196.35,
      "margin": 91.78,
      "free_margin": 3104.57,
      "margin_level": 3482.62,
      "profit": 25.55,
      "last_updated": "2026-01-12T11:14:28Z",
      "active_eas": [
        "GoldenTrade"
      ]
    },
    {
      "id": "80146308",
      "login": 80146308,
      "name": "IRFAN AWALUDIN",
      "server": "WindsorBrokers1-Real1",
      "currency": "USC",
      "balance": 166459,
      "equity": 167359,
      "margin": 6885.35,
      "free_margin": 160473.65,
      "margin_level": 2430.65,
      "profit": 900,
      "last_updated": "2026-01-12T11:14:26Z",
      "active_eas": [
        "GoldenTrade"
      ]
    },
    {
      "id": "80146395",
      "login": 80146395,
      "name": "IRFAN AWALUDIN",
      "server": "WindsorBrokers1-Real1",
      "currency": "USC",
      "balance": 136878.5,
      "equity": 138284.75,
      "margin": 6884.56,
      "free_margin": 131400.19,
      "margin_level": 2008.62,
      "profit": 1406.25,
      "last_updated": "2026-01-12T11:14:28Z",
      "active_eas": [
        "GoldenTrade"
      ]
    },
    {
      "id": "80146428",
      "login": 80146428,
      "name": "FERRI SYAFRIADI",
      "server": "WindsorBrokers1-Real1",
      "currency": "USC",
      "balance": 3099.8,
      "equity": 3119.8,
      "margin": 91.78,
      "free_margin": 3028.02,
      "margin_level": 3399.22,
      "profit": 20,
      "last_updated": "2026-01-12T11:14:51Z",
      "active_eas": [
        "GoldenTrade"
      ]
    },
    {
      "id": "80146470",
      "login": 80146470,
      "name": "NAURY NUR FUADY",
      "server": "WindsorBrokers1-Real1",
      "currency": "USC",
      "balance": 130680,
      "equity": 129315,
      "margin": 3445.88,
      "free_margin": 125869.12,
      "margin_level": 3752.74,
      "profit": -1365,
      "last_updated": "2026-01-12T11:14:41Z",
      "active_eas": [
        "GoldenTrade"
      ]
    },
    {
      "id": "80146830",
      "login": 80146830,
      "name": "ardy dwi putra",
      "server": "WindsorBrokers1-Real1",
      "currency": "USC",
      "balance": 29098.1,
      "equity": 29408.9,
      "margin": 1284.92,
      "free_margin": 28123.98,
      "margin_level": 2288.77,
      "profit": 310.8,
      "last_updated": "2026-01-12T11:14:33Z",
      "active_eas": [
        "GoldenTrade"
      ]
    },
    {
      "id": "80146857",
      "login": 80146857,
      "name": "BAYU KRESNA RAMADHANI",
      "server": "WindsorBrokers1-Real1",
      "currency": "USC",
      "balance": 0.82,
      "equity": 0.82,
      "margin": 0,
      "free_margin": 0.82,
      "margin_level": 0,
      "profit": 0,
      "last_updated": "2026-01-11T09:52:46Z",
      "active_eas": [
        "GoldenTrade"
      ]
    },
    {
      "id": "80146904",
      "login": 80146904,
      "name": "darmadi darmadi",
      "server": "WindsorBrokers1-Real1",
      "currency": "USC",
      "balance": 3170.4,
      "equity": 3183.3,
      "margin": 91.78,
      "free_margin": 3091.52,
      "margin_level": 3468.4,
      "profit": 12.9,
      "last_updated": "2026-01-12T11:15:12Z",
      "active_eas": [
        "GoldenTrade"
      ]
    },
    {
      "id": "80146918",
      "login": 80146918,
      "name": "YUNUS YUNUS",
      "server": "WindsorBrokers1-Real1",
      "currency": "USC",
      "balance": 2813.25,
      "equity": 2832.75,
      "margin": 91.78,
      "free_margin": 2740.97,
      "margin_level": 3086.46,
      "profit": 19.5,
      "last_updated": "2026-01-12T11:14:59Z",
      "active_eas": [
        "GoldenTrade"
      ]
    },
    {
      "id": "80147442",
      "login": 80147442,
      "name": "abdul rouf",
      "server": "WindsorBrokers1-Real1",
      "currency": "USC",
      "balance": 3171.95,
      "equity": 3209.4,
      "margin": 91.78,
      "free_margin": 3117.62,
      "margin_level": 3496.84,
      "profit": 37.45,
      "last_updated": "2026-01-12T11:13:22Z",
      "active_eas": [
        "GoldenTrade"
      ]
    },
    {
      "id": "80147444",
      "login": 80147444,
      "name": "Dini Kartikawati Prihatini",
      "server": "WindsorBrokers1-Real1",
      "currency": "USC",
      "balance": 148533.75,
      "equity": 152017.5,
      "margin": 6880.25,
      "free_margin": 145137.25,
      "margin_level": 2209.48,
      "profit": 3483.75,
      "last_updated": "2026-01-12T11:14:10Z",
      "active_eas": [
        "GoldenTrade"
      ]
    },
    {
      "id": "80147465",
      "login": 80147465,
      "name": "MUHAMMAD ADNAN ANWAR S IP",
      "server": "WindsorBrokers1-Real1",
      "currency": "USC",
      "balance": 141420,
      "equity": 148676.25,
      "margin": 3436.84,
      "free_margin": 145239.41,
      "margin_level": 4325.96,
      "profit": 7256.25,
      "last_updated": "2026-01-12T11:14:34Z",
      "active_eas": [
        "GoldenTrade"
      ]
    },
    {
      "id": "80147471",
      "login": 80147471,
      "name": "Puad Hasan",
      "server": "WindsorBrokers1-Real1",
      "currency": "USC",
      "balance": 13223,
      "equity": 13346.3,
      "margin": 550.68,
      "free_margin": 12795.62,
      "margin_level": 2423.6,
      "profit": 123.3,
      "last_updated": "2026-01-12T11:14:35Z",
      "active_eas": [
        "GoldenTrade"
      ]
    },
    {
      "id": "80147492",
      "login": 80147492,
      "name": "Anca Anca",
      "server": "WindsorBrokers1-Real1",
      "currency": "USC",
      "balance": 3170.8,
      "equity": 3194.85,
      "margin": 91.78,
      "free_margin": 3103.07,
      "margin_level": 3480.99,
      "profit": 24.05,
      "last_updated": "2026-01-12T11:14:28Z",
      "active_eas": [
        "GoldenTrade"
      ]
    },
    {
      "id": "80147811",
      "login": 80147811,
      "name": "Jusman Jusman",
      "server": "WindsorBrokers1-Real1",
      "currency": "USC",
      "balance": 3170.8,
      "equity": 3201.15,
      "margin": 91.78,
      "free_margin": 3109.37,
      "margin_level": 3487.85,
      "profit": 30.35,
      "last_updated": "2026-01-12T11:10:34Z",
      "active_eas": [
        "GoldenTrade"
      ]
    },
    {
      "id": "80147817",
      "login": 80147817,
      "name": "rinda astutik",
      "server": "WindsorBrokers1-Real1",
      "currency": "USC",
      "balance": 3170.4,
      "equity": 3184.75,
      "margin": 91.78,
      "free_margin": 3092.97,
      "margin_level": 3469.98,
      "profit": 14.35,
      "last_updated": "2026-01-12T11:15:07Z",
      "active_eas": [
        "GoldenTrade"
      ]
    },
    {
      "id": "103183855",
      "login": 103183855,
      "name": "Abi Manyu",
      "server": "FBS-Demo",
      "currency": "USD",
      "balance": 9989.83,
      "equity": 9985.43,
      "margin": 29.38,
      "free_margin": 9956.05,
      "margin_level": 33987.17,
      "profit": -4.4,
      "last_updated": "2026-01-04T08:42:25Z",
      "active_eas": [
        "EA Trade Helper",
        "GoldenTrade"
      ]
    }
  ]
}