{
  "last_updated": "2026-01-12T11:39:59Z",
  "accounts": [
    {
      "id": "0",
      "login": 0,
      "name": "",
      "server": "",
      "currency": "",
      "balance": 6727.3,
      "equity": 6727.3,
      "margin": 0,
      "free_margin": 6727.3,
      "margin_level": 0,
      "profit": 0,
      "last_updated": "2026-01-05T16:47:31Z",
      "active_eas": [
        "GoldenTrade"
      ]
    },
    {
      "id": "20158621",
      "login": 20158621,
      "name": "Eric Lanvin",
      "server": "WindsorBrokers1-Demo",
      "currency": "USC",
      "balance": 13567.45,
      "equity": 13043.1,
      "margin": 161.79,
      "free_margin": 12881.31,
      "margin_level": 8061.75,
      "profit": -524.35,
      "last_updated": "2026-01-12T10:55:44Z",
      "active_eas": [
        "EA Trade Helper"
      ]
    },
    {
      "id": "80063754",
      "login": 80063754,
      "name": "HENDRA ROHENDI",
      "server": "WindsorBrokers1-Real1",
      "currency": "USC",
      "balance": 37110,
      "equity": 37041.75,
      "margin": 688.3,
      "free_margin": 36353.45,
      "margin_level": 5381.63,
      "profit": -68.25,
      "last_updated": "2026-01-12T11:39:26Z",
      "active_eas": [
        "GoldenTrade"
      ]
    },
    {
      "id": "80068538",
      "login": 80068538,
      "name": "EKA RITAWATI",
      "server": "WindsorBrokers1-Real1",
      "currency": "USC",
      "balance": 9895.18,
      "equity": 9895.18,
      "margin": 0,
      "free_margin": 9895.18,
      "margin_level": 0,
      "profit": 0,
      "last_updated": "2026-01-05T15:38:37Z",
      "active_eas": [
        "EA Trade Helper"
      ]
    },
    {
      "id": "80075738",
      "login": 80075738,
      "name": "EKA RITAWATI",
      "server": "WindsorBrokers1-Real1",
      "currency": "USC",
      "balance": 0.36,
      "equity": 0.36,
      "margin": 0,
      "free_margin": 0.36,
      "margin_level": 0,
      "profit": 0,
      "last_updated": "2026-01-05T15:37:41Z",
      "active_eas": [
        "EA Trade Helper"
      ]
    },
    {
      "id": "80076323",
      "login": 80076323,
      "name": "Windsor cent 3",
      "server": "WITITSolutionsLtd-Real1",
      "currency": "USC",
      "balance": 10379.7,
      "equity": 10377.18,
      "margin": 4.86,
      "free_margin": 10372.32,
      "margin_level": 213522.22,
      "profit": -2.52,
      "last_updated": "2026-01-05T07:14:48Z",
      "active_eas": [
        "EA Trade Helper"
      ]
    },
    {
      "id": "80076324",
      "login": 80076324,
      "name": "Windsor cent 4",
      "server": "WITITSolutionsLtd-Real1",
      "currency": "USC",
      "balance": 6828.37,
      "equity": 6828.37,
      "margin": 0,
      "free_margin": 6828.37,
      "margin_level": 0,
      "profit": 0,
      "last_updated": "2026-01-12T10:15:58Z",
      "active_eas": [
        "EA Trade Helper"
      ]
    },
    {
      "id": "80140550",
      "login": 80140550,
      "name": "Aksan Imanuddin Rahim",
      "server": "WindsorBrokers1-Real1",
      "currency": "USC",
      "balance": 11984.55,
      "equity": 12175.05,
      "margin": 0,
      "free_margin": 12175.05,
      "margin_level": 0,
      "profit": 190.5,
      "last_updated": "2026-01-12T11:35:03Z",
      "active_eas": [
        "GoldenTrade"
      ]
    },
    {
      "id": "80144430",
      "login": 80144430,
      "name": "rusnaini rusnaini",
      "server": "WindsorBrokers1-Real1",
      "currency": "USC",
      "balance": 33489.75,
      "equity": 33890.25,
      "margin": 1377.65,
      "free_margin": 32512.6,
      "margin_level": 2460,
      "profit": 400.5,
      "last_updated": "2026-01-12T11:39:23Z",
      "active_eas": [
        "GoldenTrade"
      ]
    },
    {
      "id": "80144436",
      "login": 80144436,
      "name": "fikri fikri",
      "server": "WindsorBrokers1-Real1",
      "currency": "USC",
      "balance": 6087.4,
      "equity": 6091.3,
      "margin": 183.56,
      "free_margin": 5907.74,
      "margin_level": 3318.42,
      "profit": 3.9,
      "last_updated": "2026-01-12T11:39:36Z",
      "active_eas": [
        "GoldenTrade"
      ]
    },
    {
      "id": "80144607",
      "login": 80144607,
      "name": "Cross Masarel Lamgogo B",
      "server": "WindsorBrokers1-Real1",
      "currency": "USC",
      "balance": 8929.85,
      "equity": 8934.65,
      "margin": 275.34,
      "free_margin": 8659.31,
      "margin_level": 3244.95,
      "profit": 4.8,
      "last_updated": "2026-01-12T11:39:25Z",
      "active_eas": [
        "GoldenTrade"
      ]
    },
    {
      "id": "80144917",
      "login": 80144917,
      "name": "imran imran",
      "server": "WindsorBrokers1-Real1",
      "currency": "USC",
      "balance": 3365.45,
      "equity": 3367.1,
      "margin": 91.78,
      "free_margin": 3275.32,
      "margin_level": 3668.66,
      "profit": 1.65,
      "last_updated": "2026-01-12T11:39:39Z",
      "active_eas": [
        "GoldenTrade"
      ]
    },
    {
      "id": "80145055",
      "login": 80145055,
      "name": "putri nurlita dewi",
      "server": "WindsorBrokers1-Real1",
      "currency": "USC",
      "balance": 15187.05,
      "equity": 15042.5,
      "margin": 642.46,
      "free_margin": 14400.04,
      "margin_level": 2341.39,
      "profit": -144.55,
      "last_updated": "2026-01-12T11:35:05Z",
      "active_eas": [
        "GoldenTrade"
      ]
    },
    {
      "id": "80145216",
      "login": 80145216,
      "name": "Ardans Ardans",
      "server": "WindsorBrokers1-Real1",
      "currency": "USC",
      "balance": 9585.8,
      "equity": 9563.6,
      "margin": 550.71,
      "free_margin": 9012.89,
      "margin_level": 1736.59,
      "profit": -22.2,
      "last_updated": "2026-01-12T11:39:11Z",
      "active_eas": [
        "GoldenTrade"
      ]
    },
    {
      "id": "80145228",
      "login": 80145228,
      "name": "FAISAL FAISAL",
      "server": "WindsorBrokers1-Real1",
      "currency": "USC",
      "balance": 30515.4,
      "equity": 30091.4,
      "margin": 917.05,
      "free_margin": 29174.35,
      "margin_level": 3281.33,
      "profit": -424,
      "last_updated": "2026-01-12T11:39:21Z",
      "active_eas": [
        "GoldenTrade"
      ]
    },
    {
      "id": "80145487",
      "login": 80145487,
      "name": "DWI APRIADI",
      "server": "WindsorBrokers1-Real1",
      "currency": "USC",
      "balance": 3507.35,
      "equity": 3507.35,
      "margin": 0,
      "free_margin": 3507.35,
      "margin_level": 0,
      "profit": 0,
      "last_updated": "2026-01-12T11:39:29Z",
      "active_eas": [
        "GoldenTrade"
      ]
    },
    {
      "id": "80145852",
      "login": 80145852,
      "name": "muhammad nasir",
      "server": "WindsorBrokers1-Real1",
      "currency": "USC",
      "balance": 2926.4,
      "equity": 2929.55,
      "margin": 91.78,
      "free_margin": 2837.77,
      "margin_level": 3191.93,
      "profit": 3.15,
      "last_updated": "2026-01-12T11:39:42Z",
      "active_eas": [
        "GoldenTrade"
      ]
    },
    {
      "id": "80145993",
      "login": 80145993,
      "name": "asmah mp",
      "server": "WindsorBrokers1-Real1",
      "currency": "USC",
      "balance": 2270.8,
      "equity": 2274.35,
      "margin": 91.78,
      "free_margin": 2182.57,
      "margin_level": 2478.05,
      "profit": 3.55,
      "last_updated": "2026-01-12T11:39:28Z",
      "active_eas": [
        "GoldenTrade"
      ]
    },
    {
      "id": "80145997",
      "login": 80145997,
      "name": "Hj Suriani",
      "server": "WindsorBrokers1-Real1",
      "currency": "USC",
      "balance": 2270.3,
      "equity": 2271.9,
      "margin": 91.78,
      "free_margin": 2180.12,
      "margin_level": 2475.38,
      "profit": 1.6,
      "last_updated": "2026-01-12T11:39:39Z",
      "active_eas": [
        "GoldenTrade"
      ]
    },
    {
      "id": "80146009",
      "login": 80146009,
      "name": "Muhammad Sukriyadi",
      "server": "WindsorBrokers1-Real1",
      "currency": "USC",
      "balance": 5342,
      "equity": 5302.7,
      "margin": 183.56,
      "free_margin": 5119.14,
      "margin_level": 2888.81,
      "profit": -39.3,
      "last_updated": "2026-01-12T11:35:02Z",
      "active_eas": [
        "GoldenTrade"
      ]
    },
    {
      "id": "80146014",
      "login": 80146014,
      "name": "Arif Fadeli Badarrusmanto",
      "server": "WindsorBrokers1-Real1",
      "currency": "USC",
      "balance": 2770.8,
      "equity": 2750.55,
      "margin": 91.78,
      "free_margin": 2658.77,
      "margin_level": 2996.89,
      "profit": -20.25,
      "last_updated": "2026-01-12T11:35:10Z",
      "active_eas": [
        "GoldenTrade"
      ]
    },
    {
      "id": "80146232",
      "login": 80146232,
      "name": "suwardi dwi cahyono",
      "server": "WindsorBrokers1-Real1",
      "currency": "USC",
      "balance": 3170.8,
      "equity": 3171.95,
      "margin": 91.78,
      "free_margin": 3080.17,
      "margin_level": 3456.04,
      "profit": 1.15,
      "last_updated": "2026-01-12T11:39:28Z",
      "active_eas": [
        "GoldenTrade"
      ]
    },
    {
      "id": "80146308",
      "login": 80146308,
      "name": "IRFAN AWALUDIN",
      "server": "WindsorBrokers1-Real1",
      "currency": "USC",
      "balance": 164209,
      "equity": 163402.75,
      "margin": 0,
      "free_margin": 163402.75,
      "margin_level": 0,
      "profit": -806.25,
      "last_updated": "2026-01-12T11:39:27Z",
      "active_eas": [
        "GoldenTrade"
      ]
    },
    {
      "id": "80146395",
      "login": 80146395,
      "name": "IRFAN AWALUDIN",
      "server": "WindsorBrokers1-Real1",
      "currency": "USC",
      "balance": 134628.5,
      "equity": 133439.75,
      "margin": 0,
      "free_margin": 133439.75,
      "margin_level": 0,
      "profit": -1188.75,
      "last_updated": "2026-01-12T11:39:28Z",
      "active_eas": [
        "GoldenTrade"
      ]
    },
    {
      "id": "80146428",
      "login": 80146428,
      "name": "FERRI SYAFRIADI",
      "server": "WindsorBrokers1-Real1",
      "currency": "USC",
      "balance": 3099.8,
      "equity": 3102.3,
      "margin": 91.78,
      "free_margin": 3010.52,
      "margin_level": 3380.15,
      "profit": 2.5,
      "last_updated": "2026-01-12T11:39:52Z",
      "active_eas": [
        "GoldenTrade"
      ]
    },
    {
      "id": "80146470",
      "login": 80146470,
      "name": "NAURY NUR FUADY",
      "server": "WindsorBrokers1-Real1",
      "currency": "USC",
      "balance": 128430,
      "equity": 127983.75,
      "margin": 3441.38,
      "free_margin": 124542.37,
      "margin_level": 3718.97,
      "profit": -446.25,
      "last_updated": "2026-01-12T11:39:42Z",
      "active_eas": [
        "GoldenTrade"
      ]
    },
    {
      "id": "80146830",
      "login": 80146830,
      "name": "ardy dwi putra",
      "server": "WindsorBrokers1-Real1",
      "currency": "USC",
      "balance": 29098.1,
      "equity": 29137.3,
      "margin": 1284.92,
      "free_margin": 27852.38,
      "margin_level": 2267.64,
      "profit": 39.2,
      "last_updated": "2026-01-12T11:39:32Z",
      "active_eas": [
        "GoldenTrade"
      ]
    },
    {
      "id": "80146857",
      "login": 80146857,
      "name": "BAYU KRESNA RAMADHANI",
      "server": "WindsorBrokers1-Real1",
      "currency": "USC",
      "balance": 0.82,
      "equity": 0.82,
      "margin": 0,
      "free_margin": 0.82,
      "margin_level": 0,
      "profit": 0,
      "last_updated": "2026-01-11T09:52:46Z",
      "active_eas": [
        "GoldenTrade"
      ]
    },
    {
      "id": "80146904",
      "login": 80146904,
      "name": "darmadi darmadi",
      "server": "WindsorBrokers1-Real1",
      "currency": "USC",
      "balance": 3170.4,
      "equity": 3150.1,
      "margin": 91.78,
      "free_margin": 3058.32,
      "margin_level": 3432.23,
      "profit": -20.3,
      "last_updated": "2026-01-12T11:35:12Z",
      "active_eas": [
        "GoldenTrade"
      ]
    },
    {
      "id": "80146918",
      "login": 80146918,
      "name": "YUNUS YUNUS",
      "server": "WindsorBrokers1-Real1",
      "currency": "USC",
      "balance": 2813.25,
      "equity": 2821.25,
      "margin": 91.78,
      "free_margin": 2729.47,
      "margin_level": 3073.93,
      "profit": 8,
      "last_updated": "2026-01-12T11:39:59Z",
      "active_eas": [
        "GoldenTrade"
      ]
    },
    {
      "id": "80147442",
      "login": 80147442,
      "name": "abdul rouf",
      "server": "WindsorBrokers1-Real1",
      "currency": "USC",
      "balance": 3171.95,
      "equity": 3162.5,
      "margin": 91.78,
      "free_margin": 3070.72,
      "margin_level": 3445.74,
      "profit": -9.45,
      "last_updated": "2026-01-12T11:38:23Z",
      "active_eas": [
        "GoldenTrade"
      ]
    },
    {
      "id": "80147444",
      "login": 80147444,
      "name": "Dini Kartikawati Prihatini",
      "server": "WindsorBrokers1-Real1",
      "currency": "USC",
      "balance": 146283.75,
      "equity": 149340,
      "margin": 0,
      "free_margin": 149340,
      "margin_level": 0,
      "profit": 3056.25,
      "last_updated": "2026-01-12T11:39:10Z",
      "active_eas": [
        "GoldenTrade"
      ]
    },
    {
      "id": "80147465",
      "login": 80147465,
      "name": "MUHAMMAD ADNAN ANWAR S IP",
      "server": "WindsorBrokers1-Real1",
      "currency": "USC",
      "balance": 141420,
      "equity": 147952.5,
      "margin": 3436.84,
      "free_margin": 144515.66,
      "margin_level": 4304.9,
      "profit": 6532.5,
      "last_updated": "2026-01-12T11:39:35Z",
      "active_eas": [
        "GoldenTrade"
      ]
    },
    {
      "id": "80147471",
      "login": 80147471,
      "name": "Puad Hasan",
      "server": "WindsorBrokers1-Real1",
      "currency": "USC",
      "balance": 13223,
      "equity": 13234.7,
      "margin": 550.68,
      "free_margin": 12684.02,
      "margin_level": 2403.34,
      "profit": 11.7,
      "last_updated": "2026-01-12T11:39:36Z",
      "active_eas": [
        "GoldenTrade"
      ]
    },
    {
      "id": "80147492",
      "login": 80147492,
      "name": "Anca Anca",
      "server": "WindsorBrokers1-Real1",
      "currency": "USC",
      "balance": 3170.8,
      "equity": 3174.35,
      "margin": 91.78,
      "free_margin": 3082.57,
      "margin_level": 3458.65,
      "profit": 3.55,
      "last_updated": "2026-01-12T11:39:28Z",
      "active_eas": [
        "GoldenTrade"
      ]
    },
    {
      "id": "80147811",
      "login": 80147811,
      "name": "Jusman Jusman",
      "server": "WindsorBrokers1-Real1",
      "currency": "USC",
      "balance": 3170.8,
      "equity": 3154.65,
      "margin": 91.78,
      "free_margin": 3062.87,
      "margin_level": 3437.19,
      "profit": -16.15,
      "last_updated": "2026-01-12T11:35:35Z",
      "active_eas": [
        "GoldenTrade"
      ]
    },
    {
      "id": "80147817",
      "login": 80147817,
      "name": "rinda astutik",
      "server": "WindsorBrokers1-Real1",
      "currency": "USC",
      "balance": 3170.4,
      "equity": 3148.95,
      "margin": 91.78,
      "free_margin": 3057.17,
      "margin_level": 3430.98,
      "profit": -21.45,
      "last_updated": "2026-01-12T11:35:07Z",
      "active_eas": [
        "GoldenTrade"
      ]
    },
    {
      "id": "103183855",
      "login": 103183855,
      "name": "Abi Manyu",
      "server": "FBS-Demo",
      "currency": "USD",
      "balance": 9989.83,
      "equity": 9985.43,
      "margin": 29.38,
      "free_margin": 9956.05,
      "margin_level": 33987.17,
      "profit": -4.4,
      "last_updated": "2026-01-04T08:42:25Z",
      "active_eas": [
        "EA Trade Helper",
        "GoldenTrade"
      ]
    }
  ]
}