{
  "last_updated": "2026-01-06T03:16:52Z",
  "accounts": [
    {
      "id": "0",
      "login": 0,
      "name": "",
      "server": "",
      "currency": "",
      "balance": 6727.3,
      "equity": 6727.3,
      "margin": 0,
      "free_margin": 6727.3,
      "margin_level": 0,
      "profit": 0,
      "last_updated": "2026-01-05T16:47:31Z",
      "active_eas": [
        "GoldenTrade"
      ]
    },
    {
      "id": "20158621",
      "login": 20158621,
      "name": "Eric Lanvin",
      "server": "WindsorBrokers1-Demo",
      "currency": "USC",
      "balance": 12405.31,
      "equity": 12397.7,
      "margin": 7.5,
      "free_margin": 12390.2,
      "margin_level": 165302.67,
      "profit": -7.61,
      "last_updated": "2026-01-06T02:38:27Z",
      "active_eas": [
        "EA Trade Helper"
      ]
    },
    {
      "id": "80063754",
      "login": 80063754,
      "name": "HENDRA ROHENDI",
      "server": "WindsorBrokers1-Real1",
      "currency": "USC",
      "balance": 38638.5,
      "equity": 40416.75,
      "margin": 667.39,
      "free_margin": 39749.36,
      "margin_level": 6055.94,
      "profit": 1778.25,
      "last_updated": "2026-01-06T03:16:30Z",
      "active_eas": [
        "GoldenTrade"
      ]
    },
    {
      "id": "80068538",
      "login": 80068538,
      "name": "EKA RITAWATI",
      "server": "WindsorBrokers1-Real1",
      "currency": "USC",
      "balance": 9895.18,
      "equity": 9895.18,
      "margin": 0,
      "free_margin": 9895.18,
      "margin_level": 0,
      "profit": 0,
      "last_updated": "2026-01-05T15:38:37Z",
      "active_eas": [
        "EA Trade Helper"
      ]
    },
    {
      "id": "80075738",
      "login": 80075738,
      "name": "EKA RITAWATI",
      "server": "WindsorBrokers1-Real1",
      "currency": "USC",
      "balance": 0.36,
      "equity": 0.36,
      "margin": 0,
      "free_margin": 0.36,
      "margin_level": 0,
      "profit": 0,
      "last_updated": "2026-01-05T15:37:41Z",
      "active_eas": [
        "EA Trade Helper"
      ]
    },
    {
      "id": "80076323",
      "login": 80076323,
      "name": "Windsor cent 3",
      "server": "WITITSolutionsLtd-Real1",
      "currency": "USC",
      "balance": 10379.7,
      "equity": 10377.18,
      "margin": 4.86,
      "free_margin": 10372.32,
      "margin_level": 213522.22,
      "profit": -2.52,
      "last_updated": "2026-01-05T07:14:48Z",
      "active_eas": [
        "EA Trade Helper"
      ]
    },
    {
      "id": "80076324",
      "login": 80076324,
      "name": "Windsor cent 4",
      "server": "WITITSolutionsLtd-Real1",
      "currency": "USC",
      "balance": 7296.85,
      "equity": 7176.29,
      "margin": 142.6,
      "free_margin": 7033.69,
      "margin_level": 5032.46,
      "profit": -120.56,
      "last_updated": "2026-01-06T03:12:49Z",
      "active_eas": [
        "EA Trade Helper"
      ]
    },
    {
      "id": "80140550",
      "login": 80140550,
      "name": "Aksan Imanuddin Rahim",
      "server": "WindsorBrokers1-Real1",
      "currency": "USC",
      "balance": 14309.3,
      "equity": 14918.3,
      "margin": 222.46,
      "free_margin": 14695.84,
      "margin_level": 6706.06,
      "profit": 609,
      "last_updated": "2026-01-06T03:16:14Z",
      "active_eas": [
        "GoldenTrade"
      ]
    },
    {
      "id": "80144430",
      "login": 80144430,
      "name": "rusnaini rusnaini",
      "server": "WindsorBrokers1-Real1",
      "currency": "USC",
      "balance": 33354,
      "equity": 35280.75,
      "margin": 667.39,
      "free_margin": 34613.36,
      "margin_level": 5286.38,
      "profit": 1926.75,
      "last_updated": "2026-01-06T03:16:35Z",
      "active_eas": [
        "GoldenTrade"
      ]
    },
    {
      "id": "80144436",
      "login": 80144436,
      "name": "fikri fikri",
      "server": "WindsorBrokers1-Real1",
      "currency": "USC",
      "balance": 5748.7,
      "equity": 6010.4,
      "margin": 88.99,
      "free_margin": 5921.41,
      "margin_level": 6754.02,
      "profit": 261.7,
      "last_updated": "2026-01-06T03:16:52Z",
      "active_eas": [
        "GoldenTrade"
      ]
    },
    {
      "id": "80144607",
      "login": 80144607,
      "name": "Cross Masarel Lamgogo B",
      "server": "WindsorBrokers1-Real1",
      "currency": "USC",
      "balance": 5285.8,
      "equity": 5490.85,
      "margin": 0,
      "free_margin": 5490.85,
      "margin_level": 0,
      "profit": 205.05,
      "last_updated": "2026-01-06T03:13:40Z",
      "active_eas": [
        "GoldenTrade"
      ]
    },
    {
      "id": "80144917",
      "login": 80144917,
      "name": "imran imran",
      "server": "WindsorBrokers1-Real1",
      "currency": "USC",
      "balance": 3183.6,
      "equity": 3311.35,
      "margin": 44.49,
      "free_margin": 3266.86,
      "margin_level": 7442.91,
      "profit": 127.75,
      "last_updated": "2026-01-06T03:13:45Z",
      "active_eas": [
        "GoldenTrade"
      ]
    },
    {
      "id": "80145055",
      "login": 80145055,
      "name": "putri nurlita dewi",
      "server": "WindsorBrokers1-Real1",
      "currency": "USC",
      "balance": 13515.8,
      "equity": 14331.65,
      "margin": 311.45,
      "free_margin": 14020.2,
      "margin_level": 4601.59,
      "profit": 815.85,
      "last_updated": "2026-01-06T03:12:47Z",
      "active_eas": [
        "GoldenTrade"
      ]
    },
    {
      "id": "80145216",
      "login": 80145216,
      "name": "Ardans Ardans",
      "server": "WindsorBrokers1-Real1",
      "currency": "USC",
      "balance": 10287.8,
      "equity": 10702.7,
      "margin": 0,
      "free_margin": 10702.7,
      "margin_level": 0,
      "profit": 414.9,
      "last_updated": "2026-01-06T03:12:31Z",
      "active_eas": [
        "GoldenTrade"
      ]
    },
    {
      "id": "80145228",
      "login": 80145228,
      "name": "FAISAL FAISAL",
      "server": "WindsorBrokers1-Real1",
      "currency": "USC",
      "balance": 6305.5,
      "equity": 6685.6,
      "margin": 133.48,
      "free_margin": 6552.12,
      "margin_level": 5008.69,
      "profit": 380.1,
      "last_updated": "2026-01-06T03:13:46Z",
      "active_eas": [
        "GoldenTrade"
      ]
    },
    {
      "id": "80145487",
      "login": 80145487,
      "name": "DWI APRIADI",
      "server": "WindsorBrokers1-Real1",
      "currency": "USC",
      "balance": 3183.6,
      "equity": 3308,
      "margin": 44.49,
      "free_margin": 3263.51,
      "margin_level": 7435.38,
      "profit": 124.4,
      "last_updated": "2026-01-06T03:14:31Z",
      "active_eas": [
        "GoldenTrade"
      ]
    },
    {
      "id": "80145852",
      "login": 80145852,
      "name": "muhammad nasir",
      "server": "WindsorBrokers1-Real1",
      "currency": "USC",
      "balance": 2759.4,
      "equity": 2884.45,
      "margin": 44.49,
      "free_margin": 2839.96,
      "margin_level": 6483.37,
      "profit": 125.05,
      "last_updated": "2026-01-06T03:16:08Z",
      "active_eas": [
        "GoldenTrade"
      ]
    },
    {
      "id": "103183855",
      "login": 103183855,
      "name": "Abi Manyu",
      "server": "FBS-Demo",
      "currency": "USD",
      "balance": 9989.83,
      "equity": 9985.43,
      "margin": 29.38,
      "free_margin": 9956.05,
      "margin_level": 33987.17,
      "profit": -4.4,
      "last_updated": "2026-01-04T08:42:25Z",
      "active_eas": [
        "EA Trade Helper",
        "GoldenTrade"
      ]
    }
  ]
}