{
  "last_updated": "2026-01-16T12:26:14Z",
  "accounts": [
    {
      "id": "0",
      "login": 0,
      "name": "",
      "server": "",
      "currency": "",
      "balance": 29424,
      "equity": 29424,
      "margin": 0,
      "free_margin": 29424,
      "margin_level": 0,
      "profit": 0,
      "last_updated": "2026-01-13T15:31:28Z",
      "active_eas": [
        "GoldenTrade"
      ]
    },
    {
      "id": "20158621",
      "login": 20158621,
      "name": "Eric Lanvin",
      "server": "WindsorBrokers1-Demo",
      "currency": "USC",
      "balance": 13681.98,
      "equity": 13681.98,
      "margin": 0,
      "free_margin": 13681.98,
      "margin_level": 0,
      "profit": 0,
      "last_updated": "2026-01-12T23:41:37Z",
      "active_eas": [
        "EA Trade Helper"
      ]
    },
    {
      "id": "80062182",
      "login": 80062182,
      "name": "NUR ROSYID",
      "server": "WindsorBrokers1-Real1",
      "currency": "USC",
      "balance": 805.42,
      "equity": 806.37,
      "margin": 46.1,
      "free_margin": 760.27,
      "margin_level": 1749.18,
      "profit": 0.95,
      "last_updated": "2026-01-16T12:21:26Z",
      "active_eas": [
        "GoldenTrade"
      ]
    },
    {
      "id": "80062927",
      "login": 80062927,
      "name": "NUR ROSYID",
      "server": "WindsorBrokers1-Real1",
      "currency": "USC",
      "balance": 1329.17,
      "equity": 1327.97,
      "margin": 27.63,
      "free_margin": 1300.34,
      "margin_level": 4806.26,
      "profit": -1.2,
      "last_updated": "2026-01-16T12:25:24Z",
      "active_eas": [
        "GoldenTrade"
      ]
    },
    {
      "id": "80063754",
      "login": 80063754,
      "name": "HENDRA ROHENDI",
      "server": "WindsorBrokers1-Real1",
      "currency": "USC",
      "balance": 34491,
      "equity": 34873.5,
      "margin": 691.57,
      "free_margin": 34181.93,
      "margin_level": 5042.66,
      "profit": 382.5,
      "last_updated": "2026-01-16T12:25:26Z",
      "active_eas": [
        "GoldenTrade"
      ]
    },
    {
      "id": "80068538",
      "login": 80068538,
      "name": "EKA RITAWATI",
      "server": "WindsorBrokers1-Real1",
      "currency": "USC",
      "balance": 9895.18,
      "equity": 9895.18,
      "margin": 0,
      "free_margin": 9895.18,
      "margin_level": 0,
      "profit": 0,
      "last_updated": "2026-01-13T04:44:14Z",
      "active_eas": [
        "EA Trade Helper"
      ]
    },
    {
      "id": "80075738",
      "login": 80075738,
      "name": "EKA RITAWATI",
      "server": "WindsorBrokers1-Real1",
      "currency": "USC",
      "balance": 0.36,
      "equity": 0.36,
      "margin": 0,
      "free_margin": 0.36,
      "margin_level": 0,
      "profit": 0,
      "last_updated": "2026-01-05T15:37:41Z",
      "active_eas": [
        "EA Trade Helper"
      ]
    },
    {
      "id": "80076323",
      "login": 80076323,
      "name": "Windsor cent 3",
      "server": "WITITSolutionsLtd-Real1",
      "currency": "USC",
      "balance": 10379.7,
      "equity": 10377.18,
      "margin": 4.86,
      "free_margin": 10372.32,
      "margin_level": 213522.22,
      "profit": -2.52,
      "last_updated": "2026-01-05T07:14:48Z",
      "active_eas": [
        "EA Trade Helper"
      ]
    },
    {
      "id": "80076324",
      "login": 80076324,
      "name": "Windsor cent 4",
      "server": "WITITSolutionsLtd-Real1",
      "currency": "USC",
      "balance": 7368.13,
      "equity": 7368.13,
      "margin": 0,
      "free_margin": 7368.13,
      "margin_level": 0,
      "profit": 0,
      "last_updated": "2026-01-13T07:33:50Z",
      "active_eas": [
        "EA Trade Helper"
      ]
    },
    {
      "id": "80140550",
      "login": 80140550,
      "name": "Aksan Imanuddin Rahim",
      "server": "WindsorBrokers1-Real1",
      "currency": "USC",
      "balance": 12880.8,
      "equity": 12979.3,
      "margin": 230.53,
      "free_margin": 12748.77,
      "margin_level": 5630.2,
      "profit": 98.5,
      "last_updated": "2026-01-16T12:26:04Z",
      "active_eas": [
        "GoldenTrade"
      ]
    },
    {
      "id": "80144430",
      "login": 80144430,
      "name": "rusnaini rusnaini",
      "server": "WindsorBrokers1-Real1",
      "currency": "USC",
      "balance": 25374.75,
      "equity": 24972.75,
      "margin": 691.51,
      "free_margin": 24281.24,
      "margin_level": 3611.34,
      "profit": -402,
      "last_updated": "2026-01-16T12:25:22Z",
      "active_eas": [
        "GoldenTrade"
      ]
    },
    {
      "id": "80144436",
      "login": 80144436,
      "name": "fikri fikri",
      "server": "WindsorBrokers1-Real1",
      "currency": "USC",
      "balance": 5413.5,
      "equity": 5361.3,
      "margin": 92.2,
      "free_margin": 5269.1,
      "margin_level": 5814.86,
      "profit": -52.2,
      "last_updated": "2026-01-16T12:25:31Z",
      "active_eas": [
        "GoldenTrade"
      ]
    },
    {
      "id": "80144607",
      "login": 80144607,
      "name": "Cross Masarel Lamgogo B",
      "server": "WindsorBrokers1-Real1",
      "currency": "USC",
      "balance": 5825.2,
      "equity": 5905.15,
      "margin": 138.32,
      "free_margin": 5766.83,
      "margin_level": 4269.19,
      "profit": 79.95,
      "last_updated": "2026-01-16T12:25:25Z",
      "active_eas": [
        "GoldenTrade"
      ]
    },
    {
      "id": "80144917",
      "login": 80144917,
      "name": "imran imran",
      "server": "WindsorBrokers1-Real1",
      "currency": "USC",
      "balance": 2765.45,
      "equity": 2759.85,
      "margin": 46.05,
      "free_margin": 2713.8,
      "margin_level": 5993.16,
      "profit": -5.6,
      "last_updated": "2026-01-16T12:25:36Z",
      "active_eas": [
        "GoldenTrade"
      ]
    },
    {
      "id": "80145055",
      "login": 80145055,
      "name": "putri nurlita dewi",
      "server": "WindsorBrokers1-Real1",
      "currency": "USC",
      "balance": 29120.95,
      "equity": 29120.95,
      "margin": 0,
      "free_margin": 29120.95,
      "margin_level": 0,
      "profit": 0,
      "last_updated": "2026-01-13T15:30:24Z",
      "active_eas": [
        "GoldenTrade"
      ]
    },
    {
      "id": "80145216",
      "login": 80145216,
      "name": "Ardans Ardans",
      "server": "WindsorBrokers1-Real1",
      "currency": "USC",
      "balance": 10037.9,
      "equity": 10037.9,
      "margin": 0,
      "free_margin": 10037.9,
      "margin_level": 0,
      "profit": 0,
      "last_updated": "2026-01-12T19:34:27Z",
      "active_eas": [
        "GoldenTrade"
      ]
    },
    {
      "id": "80145228",
      "login": 80145228,
      "name": "FAISAL FAISAL",
      "server": "WindsorBrokers1-Real1",
      "currency": "USC",
      "balance": 0.4,
      "equity": 0.4,
      "margin": 0,
      "free_margin": 0.4,
      "margin_level": 0,
      "profit": 0,
      "last_updated": "2026-01-16T12:25:21Z",
      "active_eas": [
        "GoldenTrade"
      ]
    },
    {
      "id": "80145487",
      "login": 80145487,
      "name": "DWI APRIADI",
      "server": "WindsorBrokers1-Real1",
      "currency": "USC",
      "balance": 1535.62,
      "equity": 522.2,
      "margin": 561.14,
      "free_margin": -38.94,
      "margin_level": 93.06,
      "profit": -1013.42,
      "last_updated": "2026-01-13T18:21:06Z",
      "active_eas": [
        "GoldenTrade"
      ]
    },
    {
      "id": "80145852",
      "login": 80145852,
      "name": "muhammad nasir",
      "server": "WindsorBrokers1-Real1",
      "currency": "USC",
      "balance": 3109.1,
      "equity": 3247.45,
      "margin": 138.81,
      "free_margin": 3108.64,
      "margin_level": 2339.49,
      "profit": 138.35,
      "last_updated": "2026-01-14T12:20:01Z",
      "active_eas": [
        "GoldenTrade"
      ]
    },
    {
      "id": "80145993",
      "login": 80145993,
      "name": "asmah mp",
      "server": "WindsorBrokers1-Real1",
      "currency": "USC",
      "balance": 1881.85,
      "equity": 1908.65,
      "margin": 46.11,
      "free_margin": 1862.54,
      "margin_level": 4139.34,
      "profit": 26.8,
      "last_updated": "2026-01-16T12:25:24Z",
      "active_eas": [
        "GoldenTrade"
      ]
    },
    {
      "id": "80145997",
      "login": 80145997,
      "name": "Hj Suriani",
      "server": "WindsorBrokers1-Real1",
      "currency": "USC",
      "balance": 2016.5,
      "equity": 1991.35,
      "margin": 46.1,
      "free_margin": 1945.25,
      "margin_level": 4319.63,
      "profit": -25.15,
      "last_updated": "2026-01-16T12:25:29Z",
      "active_eas": [
        "GoldenTrade"
      ]
    },
    {
      "id": "80146009",
      "login": 80146009,
      "name": "Muhammad Sukriyadi",
      "server": "WindsorBrokers1-Real1",
      "currency": "USC",
      "balance": 4857.4,
      "equity": 4811.8,
      "margin": 92.2,
      "free_margin": 4719.6,
      "margin_level": 5218.87,
      "profit": -45.6,
      "last_updated": "2026-01-16T12:25:54Z",
      "active_eas": [
        "GoldenTrade"
      ]
    },
    {
      "id": "80146014",
      "login": 80146014,
      "name": "Arif Fadeli Badarrusmanto",
      "server": "WindsorBrokers1-Real1",
      "currency": "USC",
      "balance": 1740.88,
      "equity": 1733.88,
      "margin": 46.05,
      "free_margin": 1687.83,
      "margin_level": 3765.21,
      "profit": -7,
      "last_updated": "2026-01-16T12:26:00Z",
      "active_eas": [
        "GoldenTrade"
      ]
    },
    {
      "id": "80146232",
      "login": 80146232,
      "name": "suwardi dwi cahyono",
      "server": "WindsorBrokers1-Real1",
      "currency": "USC",
      "balance": 2399.85,
      "equity": 2398.4,
      "margin": 46.05,
      "free_margin": 2352.35,
      "margin_level": 5208.25,
      "profit": -1.45,
      "last_updated": "2026-01-16T12:25:23Z",
      "active_eas": [
        "GoldenTrade"
      ]
    },
    {
      "id": "80146308",
      "login": 80146308,
      "name": "IRFAN AWALUDIN",
      "server": "WindsorBrokers1-Real1",
      "currency": "USC",
      "balance": 100354,
      "equity": 100354,
      "margin": 0,
      "free_margin": 100354,
      "margin_level": 0,
      "profit": 0,
      "last_updated": "2026-01-14T21:19:32Z",
      "active_eas": [
        "GoldenTrade"
      ]
    },
    {
      "id": "80146395",
      "login": 80146395,
      "name": "IRFAN AWALUDIN",
      "server": "WindsorBrokers1-Real1",
      "currency": "USC",
      "balance": 100031.5,
      "equity": 100031.5,
      "margin": 0,
      "free_margin": 100031.5,
      "margin_level": 0,
      "profit": 0,
      "last_updated": "2026-01-14T21:29:21Z",
      "active_eas": [
        "GoldenTrade"
      ]
    },
    {
      "id": "80146428",
      "login": 80146428,
      "name": "FERRI SYAFRIADI",
      "server": "WindsorBrokers1-Real1",
      "currency": "USC",
      "balance": 2181.75,
      "equity": 2174.75,
      "margin": 46.05,
      "free_margin": 2128.7,
      "margin_level": 4722.58,
      "profit": -7,
      "last_updated": "2026-01-16T12:26:00Z",
      "active_eas": [
        "GoldenTrade"
      ]
    },
    {
      "id": "80146470",
      "login": 80146470,
      "name": "NAURY NUR FUADY",
      "server": "WindsorBrokers1-Real1",
      "currency": "USC",
      "balance": 100031,
      "equity": 100031,
      "margin": 0,
      "free_margin": 100031,
      "margin_level": 0,
      "profit": 0,
      "last_updated": "2026-01-14T21:32:50Z",
      "active_eas": [
        "GoldenTrade"
      ]
    },
    {
      "id": "80146830",
      "login": 80146830,
      "name": "ardy dwi putra",
      "server": "WindsorBrokers1-Real1",
      "currency": "USC",
      "balance": 18015,
      "equity": 17662.9,
      "margin": 645.41,
      "free_margin": 17017.49,
      "margin_level": 2736.69,
      "profit": -352.1,
      "last_updated": "2026-01-16T12:25:30Z",
      "active_eas": [
        "GoldenTrade"
      ]
    },
    {
      "id": "80146857",
      "login": 80146857,
      "name": "BAYU KRESNA RAMADHANI",
      "server": "WindsorBrokers1-Real1",
      "currency": "USC",
      "balance": 0.82,
      "equity": 0.82,
      "margin": 0,
      "free_margin": 0.82,
      "margin_level": 0,
      "profit": 0,
      "last_updated": "2026-01-11T09:52:46Z",
      "active_eas": [
        "GoldenTrade"
      ]
    },
    {
      "id": "80146904",
      "login": 80146904,
      "name": "darmadi darmadi",
      "server": "WindsorBrokers1-Real1",
      "currency": "USC",
      "balance": 2230.1,
      "equity": 2208.9,
      "margin": 46.1,
      "free_margin": 2162.8,
      "margin_level": 4791.54,
      "profit": -21.2,
      "last_updated": "2026-01-16T12:26:14Z",
      "active_eas": [
        "GoldenTrade"
      ]
    },
    {
      "id": "80146918",
      "login": 80146918,
      "name": "YUNUS YUNUS",
      "server": "WindsorBrokers1-Real1",
      "currency": "USC",
      "balance": 2381.25,
      "equity": 2405.1,
      "margin": 46.11,
      "free_margin": 2358.99,
      "margin_level": 5216.01,
      "profit": 23.85,
      "last_updated": "2026-01-16T12:25:43Z",
      "active_eas": [
        "GoldenTrade"
      ]
    },
    {
      "id": "80147442",
      "login": 80147442,
      "name": "abdul rouf",
      "server": "WindsorBrokers1-Real1",
      "currency": "USC",
      "balance": 2470.75,
      "equity": 2442.4,
      "margin": 46.11,
      "free_margin": 2396.29,
      "margin_level": 5296.9,
      "profit": -28.35,
      "last_updated": "2026-01-16T12:24:17Z",
      "active_eas": [
        "GoldenTrade"
      ]
    },
    {
      "id": "80147444",
      "login": 80147444,
      "name": "Dini Kartikawati Prihatini",
      "server": "WindsorBrokers1-Real1",
      "currency": "USC",
      "balance": 146013.75,
      "equity": 144348.75,
      "margin": 3458.09,
      "free_margin": 140890.66,
      "margin_level": 4174.23,
      "profit": -1665,
      "last_updated": "2026-01-16T12:24:58Z",
      "active_eas": [
        "GoldenTrade"
      ]
    },
    {
      "id": "80147465",
      "login": 80147465,
      "name": "MUHAMMAD ADNAN ANWAR S IP",
      "server": "WindsorBrokers1-Real1",
      "currency": "USC",
      "balance": 135120,
      "equity": 135120,
      "margin": 0,
      "free_margin": 135120,
      "margin_level": 0,
      "profit": 0,
      "last_updated": "2026-01-16T12:25:32Z",
      "active_eas": [
        "GoldenTrade"
      ]
    },
    {
      "id": "80147471",
      "login": 80147471,
      "name": "Puad Hasan",
      "server": "WindsorBrokers1-Real1",
      "currency": "USC",
      "balance": 7336,
      "equity": 7500.4,
      "margin": 276.63,
      "free_margin": 7223.77,
      "margin_level": 2711.35,
      "profit": 164.4,
      "last_updated": "2026-01-16T12:25:23Z",
      "active_eas": [
        "GoldenTrade"
      ]
    },
    {
      "id": "80147492",
      "login": 80147492,
      "name": "Anca Anca",
      "server": "WindsorBrokers1-Real1",
      "currency": "USC",
      "balance": 2469.7,
      "equity": 2444.5,
      "margin": 46.11,
      "free_margin": 2398.39,
      "margin_level": 5301.45,
      "profit": -25.2,
      "last_updated": "2026-01-16T12:25:07Z",
      "active_eas": [
        "GoldenTrade"
      ]
    },
    {
      "id": "80147811",
      "login": 80147811,
      "name": "Jusman Jusman",
      "server": "WindsorBrokers1-Real1",
      "currency": "USC",
      "balance": 29424,
      "equity": 29424,
      "margin": 0,
      "free_margin": 29424,
      "margin_level": 0,
      "profit": 0,
      "last_updated": "2026-01-13T15:30:51Z",
      "active_eas": [
        "GoldenTrade"
      ]
    },
    {
      "id": "80147817",
      "login": 80147817,
      "name": "rinda astutik",
      "server": "WindsorBrokers1-Real1",
      "currency": "USC",
      "balance": 2811.95,
      "equity": 2831.4,
      "margin": 46.11,
      "free_margin": 2785.29,
      "margin_level": 6140.53,
      "profit": 19.45,
      "last_updated": "2026-01-16T12:26:04Z",
      "active_eas": [
        "GoldenTrade"
      ]
    },
    {
      "id": "103183855",
      "login": 103183855,
      "name": "Abi Manyu",
      "server": "FBS-Demo",
      "currency": "USD",
      "balance": 9989.83,
      "equity": 9985.35,
      "margin": 29.38,
      "free_margin": 9955.97,
      "margin_level": 33986.9,
      "profit": -4.48,
      "last_updated": "2026-01-14T10:13:25Z",
      "active_eas": [
        "EA Trade Helper",
        "GoldenTrade"
      ]
    }
  ]
}